riscv-core/src/imem.v
`timescale 1ns / 1ps
`timescale 1ns / 1ps
/* verilator lint_off UNUSED */
module imem(
    input [31:0] addr,
    output [31:0] instr
);

reg [31:0] memory [0:255];
initial begin
 $readmemh("tests/instr_mem.hex", memory);
end

assign instr = memory[addr[9:2]]; // Assuming word-aligned addresses

endmodule
/* verilator lint_on UNUSED */

riscv-core/src/fetch.v
`timescale 1ns / 1ps

module fetch (
input  clk,
input  rst,
input [31:0] pc_next,
output [31:0] pc,
output  [31:0]  instr);

reg [31:0] pc_reg;
always @(posedge clk or posedge rst) begin
if(rst) 
    pc_reg <= 32'b0;
    else
    pc_reg <= pc_next;
end

 assign pc = pc_reg;

 imem imem_inst(
    .addr(pc_reg),
    .instr(instr)
 );
    

endmodule

riscv-core/sim/tb_fetch.v
`timescale 1ns / 1ps


module tb_fetch();
reg clk;
reg rst;
reg [31:0] pc_next;
wire [31:0] pc;
wire [31:0] instr;

fetch fetch_inst(
    .clk(clk),
    .rst(rst),
    .pc_next(pc_next),
    .pc(pc),
    .instr(instr)
);

initial begin
    clk = 0;
    /* verilator lint_off STMTDLY */
    /* verilator lint_off INFINITELOOP */
    forever #5 clk = ~clk; // 10 time units clock period
    /* verilator lint_on INFINITELOOP */
    /* verilator lint_on STMTDLY */
end 

/* verilator lint_off STMTDLY */
initial begin
    rst = 1;
    pc_next = 32'b0;
    #10
    rst = 0;
    #10
    repeat (6) begin
        pc_next = pc + 4;
        #10
        $display("%0t\t%h\t%h\taddi x1,x0,%0d", $time, pc, instr, $signed(instr[31:20]));
    end
     #10 $finish;

end
/* verilator lint_on STMTDLY */

initial begin
    $dumpfile("tb_fetch.vcd");
    $dumpvars(0, tb_fetch); 
end



endmodule

riscv-core/tb_fetch.vcd
$date
	Sat Nov 15 14:46:32 2025
$end
$version
	Icarus Verilog
$end
$timescale
	1ps
$end
$scope module tb_fetch $end
$var wire 32 ! pc [31:0] $end
$var wire 32 " instr [31:0] $end
$var reg 1 # clk $end
$var reg 32 $ pc_next [31:0] $end
$var reg 1 % rst $end
$scope module fetch_inst $end
$var wire 1 # clk $end
$var wire 32 & pc [31:0] $end
$var wire 32 ' pc_next [31:0] $end
$var wire 1 % rst $end
$var wire 32 ( instr [31:0] $end
$var reg 32 ) pc_reg [31:0] $end
$scope module imem_inst $end
$var wire 32 * addr [31:0] $end
$var wire 32 + instr [31:0] $end
$upscope $end
$upscope $end
$upscope $end
$enddefinitions $end
$comment Show the parameter values. $end
$dumpall
$end
#0
$dumpvars
b10100000000000010010011 +
b0 *
b0 )
b10100000000000010010011 (
b0 '
b0 &
1%
b0 $
0#
b10100000000000010010011 "
b0 !
$end
#5000
1#
#10000
0#
0%
#15000
1#
#20000
0#
b100 $
b100 '
#25000
b1010000000000000100010011 "
b1010000000000000100010011 (
b1010000000000000100010011 +
b100 !
b100 &
b100 )
b100 *
1#
#30000
0#
b1000 $
b1000 '
#35000
b1000001000000110110011 "
b1000001000000110110011 (
b1000001000000110110011 +
b1000 !
b1000 &
b1000 )
b1000 *
1#
#40000
0#
b1100 $
b1100 '
#45000
b110010000000000001000010011 "
b110010000000000001000010011 (
b110010000000000001000010011 +
b1100 !
b1100 &
b1100 )
b1100 *
1#
#50000
0#
b10000 $
b10000 '
#55000
bx "
bx (
bx +
b10000 !
b10000 &
b10000 )
b10000 *
1#
#60000
0#
b10100 $
b10100 '
#65000
b10100 !
b10100 &
b10100 )
b10100 *
1#
#70000
0#
b11000 $
b11000 '
#75000
b11000 !
b11000 &
b11000 )
b11000 *
1#
